{"title":"教务处本科生招生办公室人员信息","author":"Mr.Hope","time":"2021年12月3日","shareable":true,"content":[["title",{"text":"副主任"}],["ul",{"heading":"郑伟","text":["办公地点: 校本部综合行政楼225","办公电话: 0431-85098500/85098801","电子信箱: zhengw764@nenu.edu.cn","工作职责: 援藏"]}],["ul",{"heading":"孟祥锋","text":["办公地点: 校本部综合行政楼225","办公电话: 0431-85098500/85098801","电子信箱: mengxf940@nenu.edu.cn","工作职责: 负责本科生招生宣传工作(线上)"]}],["title",{"text":"职员"}],["ul",{"heading":"陈丽莉","text":["办公地点: 校本部行政楼218，净月校区行政办公楼225","办公电话: 0431-85098500","电子信箱: chenll931@nenu.edu.cn","工作职责: 负责本科生招生管理工作"]}],["ul",{"heading":"于尧","text":["办公地点: 校本部行政楼225","办公电话: 0431-85098801","电子信箱: yuy462@nenu.edu.cn","工作职责: 负责本科生招生宣传工作(线下)"]}],["ul",{"heading":"刘恬恬","text":["办公地点: 校本部综合行政楼225","办公电话: 0431-85098500/85098801","电子信箱: liutt392@nenu.edu.cn","工作职责: 负责本科生招生管理工作"]}],["ul",{"heading":"李建楠","text":["办公地点: 校本部综合行政楼225","办公电话: 0431-85098500/85098801","电子信箱: lijn092@nenu.edu.cn","工作职责: 负责本科生招生管理工作"]}]],"cite":[],"id":"intro/apt/course/info/enroll"}