{"title":"净月美食节","author":"Mr.Hope","time":"2021年11月22日","shareable":true,"content":[["img",{"src":"https://mp.innenu.com/img/dining/dining36.jpg"}],["img",{"src":"https://mp.innenu.com/img/dining/dining37.jpg"}],["img",{"src":"https://mp.innenu.com/img/dining/dining38.jpg"}],["img",{"src":"https://mp.innenu.com/img/dining/dining39.jpg"}]],"cite":[],"id":"guide/dining/festival/jingyue","images":["https://mp.innenu.com/img/dining/dining36.jpg","https://mp.innenu.com/img/dining/dining37.jpg","https://mp.innenu.com/img/dining/dining38.jpg","https://mp.innenu.com/img/dining/dining39.jpg"]}