{"title":"客户端新生课程添加","time":"2022 年 8 月 9 日","shareable":true,"id":"guide/yiban/add/mobile","author":"Mr.Hope","cite":[],"content":[{"tag":"text","text":["点击图中的『精品优程』 ↓"]},{"tag":"img","src":"https://mp.innenu.com/img/yiban/mobile-add1.png"},{"tag":"text","text":["之后点击右下角『课群』 ↓"]},{"tag":"img","src":"$img/yiban/mobile-add2.jpg"},{"tag":"text","text":["点击下方的『添加课程』 ↓"]},{"tag":"img","src":"https://mp.innenu.com/img/yiban/mobile-add4.jpg"},{"tag":"text","text":["输入『V5LUHDRN』 ↓"]},{"tag":"action","content":"V5LUHDRN"},{"tag":"img","src":"https://mp.innenu.com/img/yiban/mobile-add3.png"},{"tag":"text","text":["选择自己的学院并加入 ↓"]},{"tag":"img","src":"https://mp.innenu.com/img/yiban/mobile-add6.jpg"}]}